{
    "title": "President Donald J. Trump Signed S. 2152 into Law – The White House",
    "link": "https://trumpwhitehouse.archives.gov/briefings-statements/president-donald-j-trump-signed-s-2152-law/",
    "created_at": "2018-12-07T00:00:00",
    "content": "\n\t\t\t\tStatements & Releases\t\t\t\n\n\t\tLaw & Justice\t\n\nIssued on:\nDecember 7, 2018\nOn Friday, December 7, 2018, the President signed into law:S. 2152, the “Amy, Vicky, and Andy Child Pornography Victim Assistance Act of 2018,” which requires Federal courts to order mandatory restitution against a defendant who is convicted for trafficking in child pornography.",
    "president": null
}