{
    "title": "President Donald J. Trump Signs S. 2155 into Law – The White House",
    "link": "https://trumpwhitehouse.archives.gov/briefings-statements/president-donald-j-trump-signs-s-2155-law/",
    "created_at": "2018-05-24T00:00:00",
    "content": "\n\t\t\t\tStatements & Releases\t\t\t\n\n\t\tEconomy & Jobs\t\n\nIssued on:\nMay 24, 2018\nOn Thursday, May 24, 2018, the President signed into law:2155, the “Economic Growth, Regulatory Relief, and Consumer Protection Act,” which provides, among other things:  (1) exemptions to mortgage lending rules; (2) regulatory relief for community banks, bank holding companies, and securities regulations; (3) consumer protections for veterans and certain homeowners; and (4) protections for student loan borrowers.",
    "president": null
}