{
    "title": "Bill Announcement – The White House",
    "link": "https://trumpwhitehouse.archives.gov/briefings-statements/bill-announcement-100120-2/",
    "created_at": "2020-10-01T00:00:00",
    "content": "\n\t\t\t\tStatements & Releases\t\t\t\n\n\t\tBudget & Spending\t\n\nIssued on:\nOctober 1, 2020\nOn Thursday, October 1, 2020, the President signed into law:S. 2193, the “Charging Helps Agencies Realize General Efficiencies Act” or the “CHARGE Act,” which requires the General Services Administration to issue guidance to clarify that Federal agencies may pay by charge card for the charging of Federal electric motor vehicles; andS. 3105, which designates a facility of the United States Postal Service located at 456 North Meridian Street in Indianapolis, Indiana, as the Richard G. Lugar Post Office.",
    "president": null
}