{
    "title": "President Donald J. Trump Signs S. 2245 and S. 2850 into Law – The White House",
    "link": "https://trumpwhitehouse.archives.gov/briefings-statements/president-donald-j-trump-signs-s-2245-s-2850-law/",
    "created_at": "2018-08-01T00:00:00",
    "content": "\n\t\t\t\tStatements & Releases\t\t\t\n\n\t\tLand & Agriculture\t\n\nIssued on:\nAugust 1, 2018\nOn Wednesday, August 1, 2018, the President signed into law:S. 2245, the “Knowledgeable Innovators and Worthy Investors Act or the KIWI Act,” which makes New Zealand nationals eligible to enter the United States as nonimmigrant traders and investors provided New Zealand grants reciprocal treatment to U.S. nationals; andS. 2850, which amends the White Mountain Apache Tribe Water (WMAT) Rights Quantification Act of 2010 to add other uses of the WMAT Settlement Fund; and the Long-Term Leasing Act of 1955 to authorize 99-year leases for all lands within the boundaries of the Santa Clara and Ohkay Owingeh Pueblos.",
    "president": null
}