{
    "title": "Readout of President Donald J. Trump’s Call with Emir Tamim bin Hamad Al Thani of Qatar – The White House",
    "link": "https://trumpwhitehouse.archives.gov/briefings-statements/readout-president-donald-j-trumps-call-emir-tamim-bin-hamad-al-thani-qatar-4/",
    "created_at": "2018-06-15T00:00:00",
    "content": "\n\t\t\t\tStatements & Releases\t\t\t\n\n\t\tForeign Policy\t\n\nIssued on:\nJune 15, 2018\nPresident Donald J. Trump spoke yesterday with Emir Tamim bin Hamad Al Thani of Qatar.  The leaders discussed ongoing cooperation between the United States and Qatar and the importance of Gulf unity to mitigate regional security threats and to ensure the region’s economic prosperity.",
    "president": null
}