{
    "title": "President Donald J. Trump Is Taking a Bold New Approach to Advance Kidney Health – The White House",
    "link": "https://trumpwhitehouse.archives.gov/briefings-statements/president-donald-j-trump-taking-bold-new-approach-advance-kidney-health/",
    "created_at": "2019-07-10T00:00:00",
    "content": "\n\t\t\t\tFact Sheets\t\t\t\n\n\t\tHealthcare\t\n\nIssued on:\nJuly 10, 2019\nWe believe in giving patients choice and freedom in healthcare, ensuring access to the doctors they want, the treatments they need, and the highest standard of medical care anywhere in the world.\n\t\t\t\t\t\tPresident Donald J. Trump\t\t\t\t\tADVANCING KIDNEY HEALTH: President Donald J. Trump signed an executive order aimed at improving kidney health and promoting increased treatment options for American patients. IMPROVING TREATMENT OPTIONS: The current quality of care for patients with kidney disease is unacceptable and treatment options are far too expensive.   TAKING A NEW APPROACH: President Trump has refused to accept the status quo and has taken an innovative approach to deliver new treatment options for major diseases.",
    "president": null
}