{
    "title": "President Donald J. Trump’s First Year of Foreign Policy Accomplishments – The White House",
    "link": "https://trumpwhitehouse.archives.gov/briefings-statements/president-donald-j-trumps-first-year-of-foreign-policy-accomplishments/",
    "created_at": "2017-12-19T00:00:00",
    "content": "\n\t\t\t\tFact Sheets\t\t\t\n\n\t\tForeign Policy\t\n\nIssued on:\nDecember 19, 2017\nSo let this be our mission, and let this be our message to the world: We will fight together, sacrifice together, and stand together for peace, for freedom, for justice, for family, for humanity, and for the almighty God who made us all.\n\t\t\t\t\t\tPresident Donald J. Trump\t\t\t\t\tAN AMERICA FIRST FOREIGN POLICY: President Donald J. Trump has fulfilled his promise to put America First by prioritizing the defense of America’s borders at home and its interests abroad.PROTECT THE HOMELAND: President Trump has taken innovative and aggressive action to protect our people and eliminate threats to the homeland at their source.PEACE THROUGH STRENGTH: President Trump is rebuilding our military, and has revitalized international partnerships and prompted our allies to take on a greater share of the burden of collective defense.ENHANCING AMERICAN INFLUENCE: President Trump has made historic trips and delivered speeches abroad restoring America’s influence around the world.",
    "president": null
}