{
    "title": "President Donald J. Trump’s Administration is Advancing a Free and Open Indo-Pacific – The White House",
    "link": "https://trumpwhitehouse.archives.gov/briefings-statements/president-donald-j-trumps-administration-advancing-free-open-indo-pacific/",
    "created_at": "2018-07-30T00:00:00",
    "content": "\n\t\t\t\tFact Sheets\t\t\t\n\n\t\tEconomy & Jobs\t\n\nIssued on:\nJuly 30, 2018\nINDO-PACIFIC BUSINESS FORUM: Administration officials reaffirmed a whole-of-government commitment to enhancing economic and commercial engagement in the Indo-Pacific region.   A STRATEGIC INVESTMENT:  The Trump Administration announced $113.5 million in immediate funding to seed new strategic initiatives in the Indo-Pacific region. COOPERATION WITH PARTNERS: The Trump Administration announced a range of new economic cooperation efforts with Japan, Australia, India, and Mongolia.  ",
    "president": null
}