{
    "title": "President Donald J. Trump’s America First Vision for Keeping Our Nation Safe – The White House",
    "link": "https://trumpwhitehouse.archives.gov/briefings-statements/president-donald-j-trumps-america-first-vision-for-keeping-our-nation-safe/",
    "created_at": "2019-02-05T00:00:00",
    "content": "\n\t\t\t\tFact Sheets\t\t\t\n\n\t\tNational Security & Defense\t\n\nIssued on:\nFebruary 5, 2019\nWe will no longer use American military might to construct democracies in faraway lands, or try to rebuild other countries in our own image. Those days are now over. Instead, we will work with allies and partners to protect our shared interests.\n\t\t\t\t\t\tPresident Donald J. Trump\t\t\t\t\tSAFETY THROUGH STRENGTH: President Donald J. Trump has undertaken historic efforts to rebuild our military and strengthen our Nation’s defenses. PUTTING AMERICA FIRST: President Trump is fulfilling his promise to stop the cycle of endless wars that have burdened our Nation. ",
    "president": null
}